bit_login/__init__.py
bit_login/config.py
bit_login/login.py
bit_login/service.py
bit_login-2.0.0.dist-info/METADATA
bit_login-2.0.0.dist-info/WHEEL
bit_login-2.0.0.dist-info/top_level.txt
bit_login-2.0.0.dist-info/RECORD
