Metadata-Version: 2.4
Name: bit_login
Version: 2.0.0
Summary: 北京理工大学统一身份验证登录模块
Author: teclab
Author-email: admin@teclab.org.cn
Keywords: BIT,BITCAS,BITLogin,BITWebVPN,BITSSO,BITSSOLogin,BITSSOClient
Classifier: Programming Language :: Python :: 3
Classifier: Operating System :: OS Independent
Requires-Python: >=3.6
Dynamic: author
Dynamic: author-email
Dynamic: classifier
Dynamic: description
Dynamic: description-content-type
Dynamic: keywords
Dynamic: requires-python
Dynamic: summary
